filevisualization/__init__.py
filevisualization/cli.py
filevisualization/core.py
filevisualization/py.typed
filevisualization/style_utils.py
filevisualization/styles.py
filevisualization/renderers/mindmap_renderer.py
filevisualization/renderers/plotly_renderer.py
filevisualization/renderers/pyvis_renderer.py
filevisualization/renderers/tree_renderer.py
filevisualization-0.1.0.dist-info/licenses/LICENSE
filevisualization-0.1.0.dist-info/METADATA
filevisualization-0.1.0.dist-info/WHEEL
filevisualization-0.1.0.dist-info/entry_points.txt
filevisualization-0.1.0.dist-info/top_level.txt
filevisualization-0.1.0.dist-info/RECORD
