Metadata-Version: 2.4
Name: filevisualization
Version: 0.1.0
Summary: Visualize structure of XML/JSON/YAML/TOML as trees or mind maps
Author: hayashikunita
License: MIT
Project-URL: Homepage, https://github.com/hayashikunita/filevisualization
Project-URL: Repository, https://github.com/hayashikunita/filevisualization
Project-URL: Issues, https://github.com/hayashikunita/filevisualization/issues
Keywords: visualization,xml,json,yaml,toml,tree,mindmap
Classifier: Programming Language :: Python :: 3
Classifier: Programming Language :: Python :: 3.10
Classifier: Programming Language :: Python :: 3.11
Classifier: Programming Language :: Python :: 3.12
Classifier: License :: OSI Approved :: MIT License
Classifier: Operating System :: OS Independent
Classifier: Topic :: Utilities
Requires-Python: >=3.10
License-File: LICENSE
Requires-Dist: rich>=13.7
Requires-Dist: pyyaml>=6
Requires-Dist: tomli>=2; python_version < "3.11"
Requires-Dist: graphviz>=0.20.3
Requires-Dist: defusedxml>=0.7.1
Provides-Extra: all
Requires-Dist: plotly>=5.24.0; extra == "all"
Requires-Dist: pyvis>=0.3.2; extra == "all"
Requires-Dist: ijson>=3.2.3; extra == "all"
Requires-Dist: ruff>=0.5; extra == "all"
Requires-Dist: mypy>=1.10; extra == "all"
Requires-Dist: bandit>=1.7; extra == "all"
Provides-Extra: plotly
Requires-Dist: plotly>=5.24.0; extra == "plotly"
Provides-Extra: pyvis
Requires-Dist: pyvis>=0.3.2; extra == "pyvis"
Provides-Extra: stream
Requires-Dist: ijson>=3.2.3; extra == "stream"
Dynamic: license-file
